svgdatagrabber/__init__.py
svgdatagrabber/_version.py
svgdatagrabber/parser.py
svgdatagrabber/version.py
svgdatagrabber/filters/__init__.py
svgdatagrabber/filters/closedpath.py
svgdatagrabber/filters/custom.py
svgdatagrabber/filters/filterbase.py
svgdatagrabber/filters/rectangle.py
svgdatagrabber/filters/segmentnumber.py
svgdatagrabber/filters/specialline.py
svgdatagrabber/geometry/__init__.py
svgdatagrabber/geometry/arc.py
svgdatagrabber/geometry/bezier.py
svgdatagrabber/geometry/circle.py
svgdatagrabber/geometry/closedshape.py
svgdatagrabber/geometry/csys.py
svgdatagrabber/geometry/ellipse.py
svgdatagrabber/geometry/exceptions.py
svgdatagrabber/geometry/geometrybase.py
svgdatagrabber/geometry/linebase.py
svgdatagrabber/geometry/path.py
svgdatagrabber/geometry/point.py
svgdatagrabber/geometry/polygon.py
svgdatagrabber/geometry/quadrilateral.py
svgdatagrabber/geometry/sequence.py
svgdatagrabber/geometry/straightline.py
svgdatagrabber/geometry/triangle.py
svgdatagrabber/graphics/__init__.py
svgdatagrabber/graphics/__main__.py
svgdatagrabber/graphics/annotations.py
svgdatagrabber/graphics/geometricobject.py
svgdatagrabber/graphics/graphicsview.py
svgdatagrabber/graphics/mainwindow.py
svgdatagrabber-0.1.0.dist-info/LICENSE
svgdatagrabber-0.1.0.dist-info/METADATA
svgdatagrabber-0.1.0.dist-info/WHEEL
svgdatagrabber-0.1.0.dist-info/entry_points.txt
svgdatagrabber-0.1.0.dist-info/top_level.txt
svgdatagrabber-0.1.0.dist-info/RECORD
