Metadata-Version: 2.1
Name: svgdatagrabber
Version: 0.1.0
Summary: Get svg data points
Author-email: WANG Hailin <hailin.wang@connect.polyu.hk>
Project-URL: Homepage, https://github.com/haiiliin/svgdatagrabber/
Project-URL: Documentation, https://svgdatagrabber.readthedocs.io/
Classifier: Programming Language :: Python
Classifier: Programming Language :: Python :: 3
Classifier: Programming Language :: Python :: 3.8
Classifier: Programming Language :: Python :: 3.9
Classifier: Programming Language :: Python :: 3.10
Classifier: Programming Language :: Python :: 3.11
Classifier: Programming Language :: Python :: 3.12
Classifier: Programming Language :: Python :: 3.13
Classifier: Programming Language :: Python :: Implementation :: PyPy
Classifier: License :: OSI Approved :: MIT License
Classifier: Operating System :: OS Independent
Requires-Python: >=3.8
License-File: LICENSE
Requires-Dist: numpy
Requires-Dist: shapely
Requires-Dist: svgpathtools
Requires-Dist: typing_extensions
Provides-Extra: graphics
Requires-Dist: qtpy; extra == "graphics"
Requires-Dist: PyQt5; extra == "graphics"
Provides-Extra: io
Requires-Dist: matplotlib; extra == "io"
Requires-Dist: pandas; extra == "io"
Provides-Extra: dev
Requires-Dist: pytest; extra == "dev"
Requires-Dist: pytest-cov; extra == "dev"
